{
  "domain": "777hire.com",
  "vertical": "Car Rental",
  "url": "http://www.777hire.com/",
  "pageTitle": "Specialist Plant, Infrastructure & Power Hire | 777 HIRE",
  "markdown": "What are you looking for?\n\nClear\n\n![bg-blog](https://i0.wp.com/777hire.com/wp-content/uploads/2021/03/antek-0625988121.webp?fit=1920%2C839&ssl=1)\n\nSpecialist Plant, Power, and Infrastructure Hire\n\nBUILT TO SUPPORT COMPLEX PROJECTS WITH THE RIGHT EQUIPMENT\n\nFind The Right Equipment\n\nSelect CategoryVacuum ExcavationElectric Plant and ExcavatorsTemporary Power & Energy SystemsWelfare and Site AccommodationSite Security and LightingCorporate Vehicle Fleet\n\nSelect LocationSouth EastLondonSouth WestEast of EnglandYorkshire and the HumberEast MidlandsWest MidlandsNorth WestNorth East\n\nFind my rentals\n\nWe Promise To Find You The Right Equipment\n\n## Browse Our Categories\n\n[![Vacuum Excavator Hire](https://i0.wp.com/777hire.com/wp-content/uploads/2026/03/Vacuum-Excavator-Hire.webp?fit=750%2C750&ssl=1)\\\\\n\\\\\nVacuum Excavation](https://777hire.com/vehicle_type/vacuum-excavation/)\n\n[![ELECTRIC EXCAVATOR](https://i0.wp.com/777hire.com/wp-content/uploads/2026/01/ELECTRIC-EXCAVATOR.webp?fit=750%2C750&ssl=1)\\\\\n\\\\\nElectric Plant and Excavators](https://777hire.com/vehicle_type/electric-plant/)\n\n[![Temporary Power](https://i0.wp.com/777hire.com/wp-content/uploads/2026/01/Temporary-Power.webp?fit=750%2C750&ssl=1)\\\\\n\\\\\nTemporary Power & Energy Systems](https://777hire.com/vehicle_type/temporary-power/)\n\n[![Welfare](https://i0.wp.com/777hire.com/wp-content/uploads/2026/01/Welfare.webp?fit=750%2C750&ssl=1)\\\\\n\\\\\nWelfare and Site Accommodation](https://777hire.com/vehicle_type/welfare-site-accomodation/)\n\n[![Site Lighting & CCTV](https://i0.wp.com/777hire.com/wp-content/uploads/2026/03/Site-Lighting-CCTV.webp?fit=750%2C750&ssl=1)\\\\\n\\\\\nSite Security and Lighting](https://777hire.com/vehicle_type/site-security-lighting/)\n\n[![Black Mercedes-Benz V class,](https://i0.wp.com/777hire.com/wp-content/uploads/2026/01/vclass-fleet.webp?fit=750%2C500&ssl=1)\\\\\n\\\\\nCorporate Vehicle Fleet](https://777hire.com/vehicle_type/corporate-vehicle-hire/)\n\n- 24/71/7\n\n\n\n\n\nResponse Time\n\n\n\nFast quotations and availability confirmations when time critical decisions matter.\n\n- 21+10+\n\n\n\n\n\nYears In The Hire Business\n\n\n\nDeep industry experience built on reliability, relationships, and operational know how.\n\n- 100+10+\n\n\n\n\n\nVetted Suppliers\n\n\n\nCarefully selected partners meeting commercial, safety, and compliance standards.\n\n- 3.4k0k\n\n\n\n\n\nProjects Completed\n\n\n\nProven delivery across construction, infrastructure & events nationwide.\n\n\n![](https://i0.wp.com/777hire.com/wp-content/uploads/2026/01/FLEET-IMAGE.webp?fit=1140%2C760&ssl=1)\n\n## About 777 Hire\n\n777 Hire Delivers Reliable B2B Plant, Power & Infrastructure Hire Solutions For Construction, Utilities, Events & Industry.\n\n777 Hire delivers dependable B2B plant, power, and site infrastructure hire, supporting construction, utilities, events, and industrial projects with experienced coordination, trusted suppliers, and nationwide coverage.\n\n## Built For Business\n\nPurpose led hire solutions supporting complex projects across multiple sectors.\n\n## Delivered with Confidence\n\nExperienced coordination ensuring reliable supply, compliance, and on time delivery\n\n![](https://i0.wp.com/777hire.com/wp-content/uploads/2021/03/antek-0723921000.webp?fit=263%2C149&ssl=1)\n\nPowering Industry with the Right Equipment\n\n![](https://i0.wp.com/777hire.com/wp-content/uploads/2021/03/antek-0739031453.webp?fit=1%2C100&ssl=1)\n\nTalk to Our Hire Team\n\n0208 689 6861\n\n[GET STARTED](https://777hire.com/catalog/)\n\n![](https://i0.wp.com/777hire.com/wp-content/uploads/2021/03/antek-0723921000.webp?fit=263%2C149&ssl=1)\n\nSupporting Industry with Smarter Equipment Solutions\n\n[GET STARTED](https://777hire.com/catalog/)\n\nEquipment Solutions You Can Rely On\n\n## Our Happy Clients\n\nOutstanding Service That Goes Above and Beyond\n\nTop top service from this company. They do their utmost best to provide you with what you want and go above and beyond to make it happen!\n\nMr Z Miah\n\n_★_ _★_ _★_ _★_ _★_\n\nRental Customer\n\nA First Rental Experience Done Right\n\nThese guys are in a league of their own! I just had a first rental experience and it was as smooth as one can imagine\n\nMr O Pavlov\n\n_★_ _★_ _★_ _★_ _★_\n\nRental Customer\n\nConsistently Reliable Even at Short Notice\n\nWe have used the services of 777 Hire on multiple occasions now, all at short notice with specific requirements. Each hire was without fault,\n\nMr L Hill\n\n_★_ _★_ _★_ _★_ _★_\n\nRental Customer\n\nHelpful, Reliable, and Always Willing to Go the Extra Mile\n\nLovely and helpful company would use without hesitation. More than willing to go the extra mile!!\n\nMrs D Giles\n\n_★_ _★_ _★_ _★_ _★_\n\nRental Customer\n\nEquipment Solutions You Can Rely On\n\n## Latest News & Updates\n\n[view all news](https://777hire.com/news/)\n\n[![EVHIRE Is Now 777 HIRE – Same Team, Bigger Scope](https://i0.wp.com/777hire.com/wp-content/uploads/2026/02/EVHIRE-TO-777-HIRE-IMAGE.webp?fit=750%2C500&ssl=1)](https://777hire.com/evhire-is-now-777-hire/)\n\n- [Company Insights](https://777hire.com/category/company-news/ \"View all posts in Company Insights\")\n\n- February 4, 2026\n\n[EVHIRE Is Now 777 HIRE – Same Team, Bigger Scope](https://777hire.com/evhire-is-now-777-hire/)\n\nWe’re pleased to announce that EV Hire has rebranded to 777 Hire. This change reflects the natural…\n\n[Read More EVHIRE Is Now 777 HIRE – Same Team, Bigger Scope](https://777hire.com/evhire-is-now-777-hire/)\n\n[![Choosing Between Electric & Diesel Excavator Hire](https://i0.wp.com/777hire.com/wp-content/uploads/2026/01/ELECTRIC-EXCAVATOR.webp?fit=750%2C750&ssl=1)](https://777hire.com/choosing-between-electric-diesel-excavator-hire/)\n\n- [Future Technology](https://777hire.com/category/future-technology/ \"View all posts in Future Technology\")\n\n- February 1, 2026\n\n[Choosing Between Electric & Diesel Excavator Hire](https://777hire.com/choosing-between-electric-diesel-excavator-hire/)\n\nAs construction and infrastructure projects continue to evolve, plant hire decisions are no longer…\n\n[Read More Choosing Between Electric & Diesel Excavator Hire](https://777hire.com/choosing-between-electric-diesel-excavator-hire/)\n\nCall me back\n\n**Error:** Contact form not found.\n\n[Toggle photo metadata visibility](https://777hire.com/#)[Toggle photo comments visibility](https://777hire.com/#)\n\nLoading Comments...\n\nWrite a Comment...\n\nEmail (Required)Name (Required)Website",
  "scrapedAt": 1778524874639
}